.clang-format
.flake8
.gitignore
.gitmodules
CHANGELOG.md
CODEOWNERS
CODE_OF_CONDUCT
Dockerfile
Dockerfile-cuda
Dockerfile-embedded
LICENSE
MANIFEST.in
Makefile
README.md
__init__.py
description.txt
packages.txt
setup.py
./src/opendr/__init__.py
./src/opendr/_setup.py
./src/opendr/_version.py
./src/opendr/control/__init__.py
./src/opendr/engine/__init__.py
./src/opendr/engine/constants.py
./src/opendr/engine/data.py
./src/opendr/engine/datasets.py
./src/opendr/engine/example_learner.py
./src/opendr/engine/learners.py
./src/opendr/engine/target.py
./src/opendr/perception/__init__.py
./src/opendr/perception/object_detection_2d/__init__.py
./src/opendr/perception/object_detection_2d/dependencies.ini
./src/opendr/perception/object_detection_2d/centernet/README.md
./src/opendr/perception/object_detection_2d/centernet/__init__.py
./src/opendr/perception/object_detection_2d/centernet/centernet_learner.py
./src/opendr/perception/object_detection_2d/datasets/__init__.py
./src/opendr/perception/object_detection_2d/datasets/detection_dataset.py
./src/opendr/perception/object_detection_2d/datasets/transforms.py
./src/opendr/perception/object_detection_2d/datasets/wider_face.py
./src/opendr/perception/object_detection_2d/datasets/wider_person.py
./src/opendr/perception/object_detection_2d/datasets/xmldataset.py
./src/opendr/perception/object_detection_2d/detr/README.md
./src/opendr/perception/object_detection_2d/detr/__init__.py
./src/opendr/perception/object_detection_2d/detr/dependencies.ini
./src/opendr/perception/object_detection_2d/detr/detr_learner.py
./src/opendr/perception/object_detection_2d/detr/algorithm/__init__.py
./src/opendr/perception/object_detection_2d/detr/algorithm/engine.py
./src/opendr/perception/object_detection_2d/detr/algorithm/configs/model_config.yaml
./src/opendr/perception/object_detection_2d/detr/algorithm/datasets/__init__.py
./src/opendr/perception/object_detection_2d/detr/algorithm/datasets/coco.py
./src/opendr_toolkit_object_detection_2d.egg-info/PKG-INFO
./src/opendr_toolkit_object_detection_2d.egg-info/SOURCES.txt
./src/opendr_toolkit_object_detection_2d.egg-info/dependency_links.txt
./src/opendr_toolkit_object_detection_2d.egg-info/requires.txt
./src/opendr_toolkit_object_detection_2d.egg-info/top_level.txt
